gen/__init__.py
gen/nick_gen.py
rand_nick-0.3.0.dist-info/LICENSE
rand_nick-0.3.0.dist-info/METADATA
rand_nick-0.3.0.dist-info/WHEEL
rand_nick-0.3.0.dist-info/top_level.txt
rand_nick-0.3.0.dist-info/RECORD
