Metadata-Version: 2.1
Name: rand_nick
Version: 0.3.0
Summary: Генератор никнеймов
Home-page: https://github.com/dsadasdasdsaas/rand_nick
Author: vsenikizanyati
Author-email: fmsg4341@gmail.com
Classifier: Programming Language :: Python :: 3
Classifier: License :: OSI Approved :: MIT License
Classifier: Operating System :: OS Independent
Requires-Python: >=3.1
License-File: LICENSE
